{
  "groups": [
    {
      "id": "vowels",
      "title": "Vowels",
      "order": 1,
      "description": "The Sinhala vowel letters (ස්වර අකුරු)",
      "characters": [
        {"si": "අ", "roman": "a", "ipa": "/a/", "audio": "අ_fast.mp3", "meaning": "as in 'father'"},
        {"si": "ආ", "roman": "ā", "ipa": "/aː/", "audio": "ආ_fast.mp3", "meaning": "long 'a'"},
        {"si": "ඇ", "roman": "ä", "ipa": "/æ/", "audio": "ඇ_fast.mp3", "meaning": "as in 'cat'"},
        {"si": "ඈ", "roman": "ǣ", "ipa": "/æː/", "audio": "ඈ_fast.mp3", "meaning": "long 'ä'"},
        {"si": "ඉ", "roman": "i", "ipa": "/i/", "audio": "ඉ_fast.mp3", "meaning": "as in 'bit'"},
        {"si": "ඊ", "roman": "ī", "ipa": "/iː/", "audio": "ඊ_fast.mp3", "meaning": "as in 'see'"},
        {"si": "උ", "roman": "u", "ipa": "/u/", "audio": "උ_fast.mp3", "meaning": "as in 'put'"},
        {"si": "ඌ", "roman": "ū", "ipa": "/uː/", "audio": "ඌ_fast.mp3", "meaning": "as in 'food'"},
        {"si": "එ", "roman": "e", "ipa": "/e/", "audio": "එ_fast.mp3", "meaning": "as in 'bed'"},
        {"si": "ඒ", "roman": "ē", "ipa": "/eː/", "audio": "ඒ_fast.mp3", "meaning": "as in 'day'"},
        {"si": "ඔ", "roman": "o", "ipa": "/o/", "audio": "ඔ_fast.mp3", "meaning": "as in 'hot'"},
        {"si": "ඕ", "roman": "ō", "ipa": "/oː/", "audio": "ඕ_fast.mp3", "meaning": "as in 'go'"}
      ]
    },
    {
      "id": "consonants",
      "title": "Consonants",
      "order": 2,
      "description": "The Sinhala consonant letters (හල් අකුරු)",
      "characters": [
        {"si": "ක", "roman": "ka", "ipa": "/ka/", "audio": "ක_fast.mp3", "meaning": "k sound"},
        {"si": "ඛ", "roman": "kha", "ipa": "/kʰa/", "meaning": "aspirated k"},
        {"si": "ග", "roman": "ga", "ipa": "/ɡa/", "audio": "ග_fast.mp3", "meaning": "g sound"},
        {"si": "ඝ", "roman": "gha", "ipa": "/ɡʰa/", "meaning": "aspirated g"},
        {"si": "ඞ", "roman": "ṅa", "ipa": "/ŋa/", "meaning": "ng sound"},
        {"si": "ච", "roman": "ca", "ipa": "/t͡ʃa/", "meaning": "ch sound"},
        {"si": "ඡ", "roman": "cha", "ipa": "/t͡ʃʰa/", "meaning": "aspirated ch"},
        {"si": "ජ", "roman": "ja", "ipa": "/d͡ʒa/", "meaning": "j sound"},
        {"si": "ඣ", "roman": "jha", "ipa": "/d͡ʒʰa/", "meaning": "aspirated j"},
        {"si": "ඤ", "roman": "ña", "ipa": "/ɲa/", "meaning": "ny sound"},
        {"si": "ට", "roman": "ṭa", "ipa": "/ʈa/", "meaning": "retroflex t"},
        {"si": "ඨ", "roman": "ṭha", "ipa": "/ʈʰa/", "meaning": "aspirated retroflex t"},
        {"si": "ඩ", "roman": "ḍa", "ipa": "/ɖa/", "meaning": "retroflex d"},
        {"si": "ඪ", "roman": "ḍha", "ipa": "/ɖʰa/", "meaning": "aspirated retroflex d"},
        {"si": "ණ", "roman": "ṇa", "ipa": "/ɳa/", "meaning": "retroflex n"},
        {"si": "ත", "roman": "ta", "ipa": "/t̪a/", "audio": "ත_fast.mp3", "meaning": "t sound"},
        {"si": "ථ", "roman": "tha", "ipa": "/t̪ʰa/", "meaning": "aspirated t"},
        {"si": "ද", "roman": "da", "ipa": "/d̪a/", "audio": "ද_fast.mp3", "meaning": "d sound"},
        {"si": "ධ", "roman": "dha", "ipa": "/d̪ʰa/", "meaning": "aspirated d"},
        {"si": "න", "roman": "na", "ipa": "/na/", "audio": "න_fast.mp3", "meaning": "n sound"},
        {"si": "ප", "roman": "pa", "ipa": "/pa/", "audio": "ප_fast.mp3", "meaning": "p sound"},
        {"si": "ඵ", "roman": "pha", "ipa": "/pʰa/", "meaning": "aspirated p"},
        {"si": "බ", "roman": "ba", "ipa": "/ba/", "audio": "බ_fast.mp3", "meaning": "b sound"},
        {"si": "භ", "roman": "bha", "ipa": "/bʰa/", "meaning": "aspirated b"},
        {"si": "ම", "roman": "ma", "ipa": "/ma/", "audio": "ම_fast.mp3", "meaning": "m sound"},
        {"si": "ය", "roman": "ya", "ipa": "/ja/", "audio": "ය_fast.mp3", "meaning": "y sound"},
        {"si": "ර", "roman": "ra", "ipa": "/ra/", "audio": "ර_fast.mp3", "meaning": "r sound"},
        {"si": "ල", "roman": "la", "ipa": "/la/", "audio": "ල_fast.mp3", "meaning": "l sound"},
        {"si": "ව", "roman": "va", "ipa": "/ʋa/", "audio": "ව_fast.mp3", "meaning": "v/w sound"},
        {"si": "ශ", "roman": "śa", "ipa": "/ʃa/", "meaning": "sh sound"},
        {"si": "ෂ", "roman": "ṣa", "ipa": "/ʂa/", "meaning": "retroflex sh"},
        {"si": "ස", "roman": "sa", "ipa": "/sa/", "audio": "ස_fast.mp3", "meaning": "s sound"},
        {"si": "හ", "roman": "ha", "ipa": "/ha/", "audio": "හ_fast.mp3", "meaning": "h sound"},
        {"si": "ළ", "roman": "ḷa", "ipa": "/ɭa/", "meaning": "retroflex l"},
        {"si": "ෆ", "roman": "fa", "ipa": "/fa/", "meaning": "f sound"}
      ]
    },
    {
      "id": "combined-forms",
      "title": "Combined Forms",
      "order": 3,
      "description": "Consonants with vowel modifiers (පිළි)",
      "characters": [
        {"si": "කා", "roman": "kā", "ipa": "/kaː/", "meaning": "ka + ා = kā"},
        {"si": "කැ", "roman": "kä", "ipa": "/kæ/", "meaning": "ka + ැ = kä"},
        {"si": "කෑ", "roman": "kǣ", "ipa": "/kæː/", "meaning": "ka + ෑ = kǣ"},
        {"si": "කි", "roman": "ki", "ipa": "/ki/", "meaning": "ka + ි = ki"},
        {"si": "කී", "roman": "kī", "ipa": "/kiː/", "meaning": "ka + ී = kī"},
        {"si": "කු", "roman": "ku", "ipa": "/ku/", "meaning": "ka + ු = ku"},
        {"si": "කූ", "roman": "kū", "ipa": "/kuː/", "meaning": "ka + ූ = kū"},
        {"si": "කෙ", "roman": "ke", "ipa": "/ke/", "meaning": "ka + ෙ = ke"},
        {"si": "කේ", "roman": "kē", "ipa": "/keː/", "meaning": "ka + ේ = kē"},
        {"si": "කො", "roman": "ko", "ipa": "/ko/", "meaning": "ka + ො = ko"},
        {"si": "කෝ", "roman": "kō", "ipa": "/koː/", "meaning": "ka + ෝ = kō"},
        {"si": "මා", "roman": "mā", "ipa": "/maː/", "meaning": "ma + ා = mā"},
        {"si": "මැ", "roman": "mä", "ipa": "/mæ/", "meaning": "ma + ැ = mä"},
        {"si": "මි", "roman": "mi", "ipa": "/mi/", "meaning": "ma + ි = mi"},
        {"si": "මී", "roman": "mī", "ipa": "/miː/", "meaning": "ma + ී = mī"},
        {"si": "මු", "roman": "mu", "ipa": "/mu/", "meaning": "ma + ු = mu"},
        {"si": "මූ", "roman": "mū", "ipa": "/muː/", "meaning": "ma + ූ = mū"},
        {"si": "මෙ", "roman": "me", "ipa": "/me/", "meaning": "ma + ෙ = me"},
        {"si": "මේ", "roman": "mē", "ipa": "/meː/", "meaning": "ma + ේ = mē"},
        {"si": "මො", "roman": "mo", "ipa": "/mo/", "meaning": "ma + ො = mo"},
        {"si": "මෝ", "roman": "mō", "ipa": "/moː/", "meaning": "ma + ෝ = mō"}
      ]
    }
  ]
}
